bs/__init__.py
bscommon/__init__.py
bscommon-0.1.dist-info/METADATA
bscommon-0.1.dist-info/WHEEL
bscommon-0.1.dist-info/top_level.txt
bscommon-0.1.dist-info/RECORD
