Metadata-Version: 2.4
Name: bscommon
Version: 0.1
Summary: 冰鼠常用操作库
Author: bs
Requires-Dist: requests>=2.25
Requires-Dist: numpy
Dynamic: author
Dynamic: requires-dist
Dynamic: summary
